scoutr/__init__.py
scoutr/exceptions.py
scoutr/helpers/__init__.py
scoutr/helpers/api_gateway/__init__.py
scoutr/helpers/api_gateway/utils.py
scoutr/helpers/flask/__init__.py
scoutr/helpers/flask/oidc.py
scoutr/helpers/flask/routes.py
scoutr/helpers/flask/utils.py
scoutr/models/__init__.py
scoutr/models/audit.py
scoutr/models/config.py
scoutr/models/request.py
scoutr/models/user.py
scoutr/providers/__init__.py
scoutr/providers/aws/__init__.py
scoutr/providers/aws/api.py
scoutr/providers/aws/filtering.py
scoutr/providers/base/__init__.py
scoutr/providers/base/api.py
scoutr/providers/base/filtering.py
scoutr/providers/gcp/__init__.py
scoutr/providers/gcp/api.py
scoutr/providers/gcp/filtering.py
scoutr/providers/mongo/__init__.py
scoutr/providers/mongo/api.py
scoutr/providers/mongo/filtering.py
scoutr/utils/__init__.py
scoutr/utils/mock_sentry.py
scoutr/utils/utils.py
scoutr-2.1.1.dist-info/LICENSE
scoutr-2.1.1.dist-info/METADATA
scoutr-2.1.1.dist-info/WHEEL
scoutr-2.1.1.dist-info/top_level.txt
scoutr-2.1.1.dist-info/RECORD
